textaugment/__init__.py
textaugment/aeda.py
textaugment/constants.py
textaugment/eda.py
textaugment/mixup.py
textaugment/translate.py
textaugment/word2vec.py
textaugment/wordnet.py
textaugment-2.0.0.dist-info/LICENCE
textaugment-2.0.0.dist-info/METADATA
textaugment-2.0.0.dist-info/WHEEL
textaugment-2.0.0.dist-info/top_level.txt
textaugment-2.0.0.dist-info/RECORD
