Metadata-Version: 2.1
Name: textaugment
Version: 2.0.0
Summary: A library for augmenting text for natural language processing applications.
Home-page: https://github.com/dsfsi/textaugment
Author: Joseph Sefara
Author-email: sefaratj@gmail.com
License: MIT
Keywords: text augmentation,python,natural language processing,nlp
Classifier: Intended Audience :: Developers
Classifier: Natural Language :: English
Classifier: License :: OSI Approved :: MIT License
Classifier: Operating System :: OS Independent
Classifier: Programming Language :: Python :: 3
Classifier: Programming Language :: Python :: Implementation :: PyPy
Classifier: Topic :: Text Processing :: Linguistic
License-File: LICENCE
Requires-Dist: nltk
Requires-Dist: gensim>=4.0
Requires-Dist: textblob
Requires-Dist: numpy
Requires-Dist: googletrans>=2
